zapix/__init__.py
zapix/zabbix_api.py
zapix-0.0.2.dist-info/LICENSE
zapix-0.0.2.dist-info/METADATA
zapix-0.0.2.dist-info/WHEEL
zapix-0.0.2.dist-info/top_level.txt
zapix-0.0.2.dist-info/RECORD
