Metadata-Version: 2.1
Name: zapix
Version: 0.0.2
Summary: Zabbix api wrapper
Home-page: https://github.com/bakaut/zapix
Author: Nikolay Lebedev
Author-email: fifo.mail@gmail.com
License: UNKNOWN
Platform: UNKNOWN
Classifier: Programming Language :: Python :: 2
Classifier: License :: OSI Approved :: MIT License
Classifier: Operating System :: OS Independent
Requires-Python: >=2.6
